pytorch3dunet/__init__.py
pytorch3dunet/__version__.py
pytorch3dunet/predict.py
pytorch3dunet/train.py
pytorch3dunet/vis.py
pytorch3dunet/augment/__init__.py
pytorch3dunet/augment/transforms.py
pytorch3dunet/datasets/__init__.py
pytorch3dunet/datasets/dsb.py
pytorch3dunet/datasets/hdf5.py
pytorch3dunet/datasets/utils.py
pytorch3dunet/unet3d/__init__.py
pytorch3dunet/unet3d/buildingblocks.py
pytorch3dunet/unet3d/config.py
pytorch3dunet/unet3d/losses.py
pytorch3dunet/unet3d/metrics.py
pytorch3dunet/unet3d/model.py
pytorch3dunet/unet3d/predictor.py
pytorch3dunet/unet3d/se.py
pytorch3dunet/unet3d/seg_metrics.py
pytorch3dunet/unet3d/trainer.py
pytorch3dunet/unet3d/utils.py
pytorch3dunet-1.9.6.dist-info/licenses/LICENSE
pytorch3dunet-1.9.6.dist-info/METADATA
pytorch3dunet-1.9.6.dist-info/WHEEL
pytorch3dunet-1.9.6.dist-info/entry_points.txt
pytorch3dunet-1.9.6.dist-info/top_level.txt
pytorch3dunet-1.9.6.dist-info/RECORD
