Metadata-Version: 2.4
Name: pytorch3dunet
Version: 1.9.6
Summary: Versatile U-Net implementation for volumetric semantic segmentation written in PyTorch
Author: Adrian Wolny, Lorenzo Cerrone
License: MIT
Project-URL: Homepage, https://github.com/wolny/pytorch-3dunet
Requires-Python: >=3.11
License-File: LICENSE
Requires-Dist: torch
Requires-Dist: torchvision
Requires-Dist: numpy
Requires-Dist: tensorboard
Requires-Dist: tqdm
Requires-Dist: h5py
Requires-Dist: scipy
Requires-Dist: scikit-image
Requires-Dist: pyyaml
Dynamic: license-file
